setup.py
cache_ensembl/__init__.py
cache_ensembl/cache_ensembl_version.py
cache_ensembl/compara_ncbi_taxa.py
cache_ensembl/compara_orthology.py
cache_ensembl/compara_protein_tree.py
cache_ensembl/compara_species_pairs.py
cache_ensembl/core_protein_features.py
cache_ensembl/default_logger.py
cache_ensembl/dump_object.py
cache_ensembl/dump_orthology.py
cache_ensembl/general.py
cache_ensembl/marshalable_object.py
cache_ensembl/random_access_file_by_sections.py
cache_ensembl.egg-info/PKG-INFO
cache_ensembl.egg-info/SOURCES.txt
cache_ensembl.egg-info/dependency_links.txt
cache_ensembl.egg-info/top_level.txt