Metadata-Version: 1.0
Name: cache-ensembl
Version: 1.01
Summary: Fast Ensembl data cache
Home-page: http://code.google.com/p/cache-ensembl/
Author: Leo Goodstadt
Author-email: cache_ensembl@llew.org.uk
License: MIT
Keywords: GTF Ensembl gene transcript parser GFF bioinformatics science
Platform: UNKNOWN
Classifier: Intended Audience :: End Users/Desktop
Classifier: Development Status :: 5 - Production/Stable
Classifier: Intended Audience :: Developers
Classifier: Intended Audience :: Science/Research
Classifier: Intended Audience :: Information Technology
Classifier: License :: OSI Approved :: MIT License
Classifier: Programming Language :: Python
Classifier: Topic :: Scientific/Engineering
Classifier: Topic :: Scientific/Engineering :: Bio-Informatics
Classifier: Environment :: Console
